{"format":2,"version":"5.5","globals":"1143f412c1d4e8320cd04f4cb7c43d8c","files":{"flaskr___init___py":{"hash":"d4f2f6b760bf66faefd1d55f821e99b8","index":{"nums":[1,21,0,0,2,0,0],"html_filename":"flaskr___init___py.html","relative_filename":"flaskr/__init__.py"}},"flaskr_auth_py":{"hash":"6e95217cfc9f2691bb8402631a97cd04","index":{"nums":[1,60,0,0,20,0,0],"html_filename":"flaskr_auth_py.html","relative_filename":"flaskr/auth.py"}},"flaskr_blog_py":{"hash":"d07c97ee3d55659509b87428e7a7d119","index":{"nums":[1,58,0,0,16,0,0],"html_filename":"flaskr_blog_py.html","relative_filename":"flaskr/blog.py"}},"flaskr_db_py":{"hash":"bc87fc7425eabcd9d9b15015a5f94f94","index":{"nums":[1,25,0,0,4,0,0],"html_filename":"flaskr_db_py.html","relative_filename":"flaskr/db.py"}}}}